sample_rest_api/__init__.py
sample_rest_api/run.py
sample_rest_api/app/__init__.py
sample_rest_api/app/database.py
sample_rest_api/app/logger.py
sample_rest_api/app/main.py
sample_rest_api/app/seed.py
swagger_mcp/__init__.py
swagger_mcp/endpoint.py
swagger_mcp/endpoint_invoker.py
swagger_mcp/logging.py
swagger_mcp/openapi_mcp_server.py
swagger_mcp/openapi_parser.py
swagger_mcp/parse_dry_run.py
swagger_mcp/server_arg_parser.py
swagger_mcp/simple_endpoint.py
swagger_mcp/tests/__init__.py
swagger_mcp/tests/integration/conftest.py
swagger_mcp/tests/integration/test_sample_api_integration.py
swagger_mcp/tests/unit/test_const_value.py
swagger_mcp/tests/unit/test_formdata_variables.py
swagger_mcp/tests/unit/test_mixed_endpoint_variables.py
swagger_mcp/tests/unit/test_openapi_mcp_server.py
swagger_mcp/tests/unit/test_openapi_parser.py
swagger_mcp/tests/unit/test_parameter_descriptions.py
swagger_mcp/tests/unit/test_path_variables.py
swagger_mcp/tests/unit/test_query_parameter_variables.py
swagger_mcp/tests/unit/test_request_body_variables.py
swagger_mcp/tests/unit/test_schema_ref_resolution.py
swagger_mcp/tests/unit/test_tool_descriptions.py
swagger_mcp/tests/unit/test_url_usage.py
swagger_mcp-0.1.3.dist-info/METADATA
swagger_mcp-0.1.3.dist-info/WHEEL
swagger_mcp-0.1.3.dist-info/entry_points.txt
swagger_mcp-0.1.3.dist-info/top_level.txt
swagger_mcp-0.1.3.dist-info/RECORD
