Metadata-Version: 2.4
Name: swagger-mcp
Version: 0.1.3
Summary: MCP server for Swagger/OpenAPI integration
Author-email: Kyle Pena <kyle.pena@kuzco.xyz>
Project-URL: Homepage, https://github.com/context-labs/swagger-mcp
Classifier: Development Status :: 3 - Alpha
Classifier: Intended Audience :: Developers
Classifier: License :: OSI Approved :: MIT License
Classifier: Operating System :: OS Independent
Classifier: Programming Language :: Python :: 3
Classifier: Programming Language :: Python :: 3.10
Classifier: Programming Language :: Python :: 3.11
Classifier: Programming Language :: Python :: 3.12
Requires-Python: >=3.10
Requires-Dist: httpx>=0.28.1
Requires-Dist: mcp[cli]>=1.2.0
Requires-Dist: requests>=2.31.0
Requires-Dist: PyYAML~=5.3.1
Requires-Dist: fastapi>=0.95.1
Requires-Dist: uvicorn>=0.34.0
Requires-Dist: pydantic>=2.10.6
Requires-Dist: typing-extensions>=4.12.2
Requires-Dist: sqlalchemy>=1.4.48
Requires-Dist: databases[sqlite]>=0.7.0
Requires-Dist: aiosqlite>=0.18.0
Requires-Dist: python-multipart>=0.0.5
Provides-Extra: dev
Requires-Dist: pytest>=8.1.1; extra == "dev"
Requires-Dist: pytest-asyncio>=0.23.5.post1; extra == "dev"
Requires-Dist: pytest-cov>=4.1.0; extra == "dev"
Requires-Dist: python-logging-loki>=0.3.1; extra == "dev"
Requires-Dist: python-json-logger>=2.0.7; extra == "dev"
Requires-Dist: annotated-types>=0.7.0; extra == "dev"
Requires-Dist: anyio>=4.8.0; extra == "dev"
Requires-Dist: certifi>=2025.1.31; extra == "dev"
Requires-Dist: click>=8.1.8; extra == "dev"
Requires-Dist: h11>=0.14.0; extra == "dev"
Requires-Dist: httpcore>=1.0.7; extra == "dev"
Requires-Dist: httpx-sse>=0.4.0; extra == "dev"
Requires-Dist: idna>=3.10; extra == "dev"
Requires-Dist: markdown-it-py>=3.0.0; extra == "dev"
Requires-Dist: mdurl>=0.1.2; extra == "dev"
Requires-Dist: pydantic-core>=2.27.2; extra == "dev"
Requires-Dist: pydantic-settings>=2.8.1; extra == "dev"
Requires-Dist: pygments>=2.19.1; extra == "dev"
Requires-Dist: python-dotenv>=1.0.1; extra == "dev"
Requires-Dist: rich>=13.9.4; extra == "dev"
Requires-Dist: shellingham>=1.5.4; extra == "dev"
Requires-Dist: sniffio>=1.3.1; extra == "dev"
Requires-Dist: sse-starlette>=2.2.1; extra == "dev"
Requires-Dist: starlette>=0.46.1; extra == "dev"
Requires-Dist: typer>=0.15.2; extra == "dev"
